src/__init__.py
src/slack_connector.py
src/UNKNOWN.egg-info/PKG-INFO
src/UNKNOWN.egg-info/SOURCES.txt
src/UNKNOWN.egg-info/dependency_links.txt
src/UNKNOWN.egg-info/top_level.txt
src/mcp_marketplace.egg-info/PKG-INFO
src/mcp_marketplace.egg-info/SOURCES.txt
src/mcp_marketplace.egg-info/dependency_links.txt
src/mcp_marketplace.egg-info/requires.txt
src/mcp_marketplace.egg-info/top_level.txt
securaops_mcp_mpl-0.1.0.dist-info/METADATA
securaops_mcp_mpl-0.1.0.dist-info/WHEEL
securaops_mcp_mpl-0.1.0.dist-info/licenses/LICENSE
securaops_mcp_mpl-0.1.0.dist-info/RECORD
