Metadata-Version: 2.4
Name: securaops-mcp-mpl
Version: 0.1.0
Summary: A marketplace for MCP (Model Context Protocol) connectors
Project-URL: Homepage, https://github.com/securacoder/mcp-marketplace/sdks
Project-URL: Documentation, https://github.com/securacoder/mcp-marketplace/sdks#readme
Project-URL: Repository, https://github.com/securacoder/mcp-marketplace
Project-URL: Issues, https://github.com/securacoder/mcp-marketplace/issues
Author-email: Nephthali Djabon Tchounda <securaops5@gmail.com>
License-File: LICENSE
Keywords: api,connector,llm,mcp,slack
Classifier: Development Status :: 4 - Beta
Classifier: Intended Audience :: Developers
Classifier: License :: OSI Approved :: MIT License
Classifier: Programming Language :: Python :: 3
Classifier: Programming Language :: Python :: 3.8
Classifier: Programming Language :: Python :: 3.9
Classifier: Programming Language :: Python :: 3.10
Classifier: Programming Language :: Python :: 3.11
Classifier: Programming Language :: Python :: 3.12
Requires-Python: >=3.8
Requires-Dist: pydantic>=1.10.0
Requires-Dist: requests>=2.28.0
Provides-Extra: dev
Requires-Dist: black; extra == 'dev'
Requires-Dist: flake8; extra == 'dev'
Requires-Dist: mypy; extra == 'dev'
Requires-Dist: pytest; extra == 'dev'
